{"path": ".", "type": "directory", "children": [{"path": ".gitignore", "type": "file"}, {"path": "app", "type": "directory", "children": [{"path": "__init__.py", "type": "file"}, {"path": "firmware_updater_FSM.py", "type": "file"}, {"path": "current", "type": "directory", "children": [{"path": "AP_server.py", "type": "file"}, {"path": "PrinterController.py", "type": "file"}, {"path": "__init__.py", "type": "file"}, {"path": "mqtt_as.py", "type": "file"}, {"path": "__pycache__", "type": "directory", "children": [{"path": "token.cpython-38.pyc", "type": "file"}, {"path": "config.cpython-38.pyc", "type": "file"}]}, {"path": "token.py", "type": "file"}, {"path": "Network_FSM.py", "type": "file"}, {"path": "config.json", "type": "file"}, {"path": "main.py", "type": "file"}, {"path": "config.py", "type": "file"}, {"path": "version.txt", "type": "file"}, {"path": "mqtt.py", "type": "file"}, {"path": "lib", "type": "directory", "children": [{"path": "MicroWebSrv2", "type": "directory", "children": [{"path": "webRoute.py", "type": "file"}, {"path": "__init__.py", "type": "file"}, {"path": "mods", "type": "directory", "children": [{"path": "WebSockets.py", "type": "file"}, {"path": "PyhtmlTemplate.py", "type": "file"}]}, {"path": "microWebSrv2.py", "type": "file"}, {"path": "libs", "type": "directory", "children": [{"path": "urlUtils.py", "type": "file"}, {"path": "XAsyncSockets.py", "type": "file"}]}, {"path": "httpResponse.py", "type": "file"}, {"path": "httpRequest.py", "type": "file"}]}, {"path": "www", "type": "directory", "children": [{"path": "check.html", "type": "file"}, {"path": "loading.html", "type": "file"}, {"path": "loading.gif", "type": "file"}, {"path": "login.html", "type": "file"}, {"path": "styles.css", "type": "file"}, {"path": "logo.png", "type": "file"}]}]}, {"path": "CamController.py", "type": "file"}]}, {"path": ".version", "type": "file"}]}, {"path": "setup.bash", "type": "file"}, {"path": "tree.json", "type": "file"}, {"path": "version.txt", "type": "file"}, {"path": "tree_maker.py", "type": "file"}]}